optionlib/__init__.py
optionlib/menus.py
optionlib/model.py
optionlib/options.py
optionlib/data/earnings.py
optionlib/data/prices.py
optionlib/data/ticker.py
optionlib-0.0.2.dist-info/LICENSE
optionlib-0.0.2.dist-info/METADATA
optionlib-0.0.2.dist-info/WHEEL
optionlib-0.0.2.dist-info/top_level.txt
optionlib-0.0.2.dist-info/RECORD
