Metadata-Version: 2.1
Name: optionlib
Version: 0.0.2
Summary: A package for working with options data
Author: Doug.Wynne
Project-URL: Homepage, https://github.com/diego519/optionlib
Project-URL: Bug Tracker, https://github.com/diego519/optionlib/issues
Classifier: Programming Language :: Python :: 3
Classifier: License :: OSI Approved :: MIT License
Classifier: Operating System :: OS Independent
Requires-Python: >=3.8
License-File: LICENSE
